<?xml version="1.0" encoding="UTF-8"?>
<qes:espresso xsi:schemaLocation="http://www.quantum-espresso.org/ns/qes/qes-1.0 http://www.quantum-espresso.org/ns/qes/qes-1.0.xsd" Units="Hartree atomic units" xmlns:xsi="http://www.w3.org/2001/XMLSchema-instance" xmlns:qes="http://www.quantum-espresso.org/ns/qes/qes-1.0">
  <!--If not explicitely indicated, all quantities are expressed in Hartree atomic units-->
  <general_info>
    <xml_format NAME="QEXSD" VERSION="0.1.0">QEXSD_0.1.0</xml_format>
    <creator NAME="PWSCF" VERSION="6.2">XML file generated by PWSCF</creator>
    <created DATE="15Sep2020" TIME="21:33:50">This run was terminated on:  21:33:50  15 Sep 2020</created>
    <job></job>
  </general_info>
  <parallel_info>
    <nprocs>16</nprocs>
    <nthreads>1</nthreads>
    <ntasks>1</ntasks>
    <nbgrp>1</nbgrp>
    <npool>1</npool>
    <ndiag>16</ndiag>
  </parallel_info>
  <input>
    <control_variables>
      <title></title>
      <calculation>scf</calculation>
      <restart_mode>from_scratch</restart_mode>
      <prefix>scf</prefix>
      <pseudo_dir>/shared/ESPRESSO/PSLIBRARY/1.0.0/pbe/PSEUDOPOTENTIALS/</pseudo_dir>
      <outdir>./tmp/</outdir>
      <stress>true</stress>
      <forces>true</forces>
      <wf_collect>false</wf_collect>
      <disk_io>low</disk_io>
      <max_seconds>10000000</max_seconds>
      <etot_conv_thr>1.000000000000e-4</etot_conv_thr>
      <forc_conv_thr>1.000000000000e-3</forc_conv_thr>
      <press_conv_thr>5.000000000000e-1</press_conv_thr>
      <verbosity>low</verbosity>
      <print_every>100000</print_every>
    </control_variables>
    <atomic_species ntyp="1">
      <species name="Ge">
        <mass>7.264000000000000e1</mass>
        <pseudo_file>Ge.pbe-n-kjpaw_psl.1.0.0.UPF</pseudo_file>
      </species>
    </atomic_species>
    <atomic_structure nat="2" alat="7.603195148317e0">
      <atomic_positions>
        <atom name="Ge" index="1">0.000000000000000e0 0.000000000000000e0 0.000000000000000e0</atom>
        <atom name="Ge" index="2">2.688135424029828e0 2.688135424029828e0 2.688135424029828e0</atom>
      </atomic_positions>
      <cell>
        <a1>0.000000000000000e0 5.376270848059655e0 5.376270848059655e0</a1>
        <a2>5.376270848059655e0 0.000000000000000e0 5.376270848059655e0</a2>
        <a3>5.376270848059655e0 5.376270848059655e0 0.000000000000000e0</a3>
      </cell>
    </atomic_structure>
    <dft>
      <functional>PBE</functional>
      <dftU>
        <lda_plus_u_kind>0</lda_plus_u_kind>
        <Hubbard_U specie="Ge" label="4p">1.175978412713844e-1</Hubbard_U>
        <Hubbard_J0 specie="Ge" label="4p">0.000000000000000e0</Hubbard_J0>
        <Hubbard_alpha specie="Ge" label="4p">0.000000000000000e0</Hubbard_alpha>
        <Hubbard_beta specie="Ge" label="4p">0.000000000000000e0</Hubbard_beta>
        <Hubbard_J specie="Ge" label="4p">0.000000000000000e0 0.000000000000000e0 0.000000000000000e0</Hubbard_J>
        <U_projection_type>atomic</U_projection_type>
      </dftU>
    </dft>
    <spin>
      <lsda>false</lsda>
      <noncolin>false</noncolin>
      <spinorbit>false</spinorbit>
    </spin>
    <bands>
      <nbnd>7</nbnd>
      <smearing degauss="7.000000000000e-3">fd</smearing>
      <tot_charge>0.000000000000000e0</tot_charge>
      <occupations>smearing</occupations>
    </bands>
    <basis>
      <ecutwfc>2.000000000000000e1</ecutwfc>
    </basis>
    <electron_control>
      <diagonalization>davidson</diagonalization>
      <mixing_mode>plain</mixing_mode>
      <mixing_beta>7.000000000000000e-1</mixing_beta>
      <conv_thr>1.000000000000000e-6</conv_thr>
      <mixing_ndim>8</mixing_ndim>
      <max_nstep>100</max_nstep>
      <real_space_q>false</real_space_q>
      <tq_smoothing>false</tq_smoothing>
      <tbeta_smoothing>false</tbeta_smoothing>
      <diago_thr_init>0.000000000000000e0</diago_thr_init>
      <diago_full_acc>false</diago_full_acc>
      <diago_cg_maxiter>20</diago_cg_maxiter>
    </electron_control>
    <k_points_IBZ>
      <monkhorst_pack nk1="12" nk2="12" nk3="12" k1="0" k2="0" k3="0">Monkhorst-Pack</monkhorst_pack>
    </k_points_IBZ>
    <ion_control>
      <ion_dynamics>none</ion_dynamics>
      <remove_rigid_rot>false</remove_rigid_rot>
      <refold_pos>false</refold_pos>
    </ion_control>
    <cell_control>
      <cell_dynamics>none</cell_dynamics>
      <pressure>0.000000000000000e0</pressure>
      <wmass>1.324146194969766e5</wmass>
      <cell_factor>0.000000000000000e0</cell_factor>
      <free_cell rank="2" dims="3 3" order="F">
        1 1 1
        1 1 1
        1 1 1
        </free_cell>
    </cell_control>
    <symmetry_flags>
      <nosym>false</nosym>
      <nosym_evc>false</nosym_evc>
      <noinv>false</noinv>
      <no_t_rev>false</no_t_rev>
      <force_symmorphic>false</force_symmorphic>
      <use_all_frac>false</use_all_frac>
    </symmetry_flags>
  </input>
  <output>
    <convergence_info>
      <scf_conv>
        <n_scf_steps>4</n_scf_steps>
        <scf_error>5.850083205820278e-7</scf_error>
      </scf_conv>
    </convergence_info>
    <algorithmic_info>
      <real_space_q>false</real_space_q>
      <uspp>true</uspp>
      <paw>true</paw>
    </algorithmic_info>
    <atomic_species ntyp="1" pseudo_dir="/shared/ESPRESSO/PSLIBRARY/1.0.0/pbe/PSEUDOPOTENTIALS/">
      <species name="Ge">
        <mass>7.264000000000000e1</mass>
        <pseudo_file>Ge.pbe-n-kjpaw_psl.1.0.0.UPF</pseudo_file>
      </species>
    </atomic_species>
    <atomic_structure nat="2" alat="1.889726132886e0">
      <atomic_positions>
        <atom name="Ge" index="1">0.000000000000000e0 0.000000000000000e0 0.000000000000000e0</atom>
        <atom name="Ge" index="2">2.688135424029828e0 2.688135424029828e0 2.688135424029828e0</atom>
      </atomic_positions>
      <cell>
        <a1>0.000000000000000e0 5.376270848059655e0 5.376270848059655e0</a1>
        <a2>5.376270848059655e0 0.000000000000000e0 5.376270848059655e0</a2>
        <a3>5.376270848059655e0 5.376270848059655e0 0.000000000000000e0</a3>
      </cell>
    </atomic_structure>
    <symmetries>
      <nsym>48</nsym>
      <nrot>48</nrot>
      <space_group>0</space_group>
      <symmetry>
        <info name="identity">crystal_symmetry</info>
        <rotation rank="2" dims="3 3" order="F">
          1.000000000000000e0 0.000000000000000e0 0.000000000000000e0
          0.000000000000000e0 1.000000000000000e0 0.000000000000000e0
          0.000000000000000e0 0.000000000000000e0 1.000000000000000e0
          </rotation>
        <fractional_translation>0.000000000000000e0 0.000000000000000e0 0.000000000000000e0</fractional_translation>
        <equivalent_atoms nat="2" size="2">1 2</equivalent_atoms>
      </symmetry>
      <symmetry>
        <info name="180 deg rotation - cart. axis [0,0,1]">crystal_symmetry</info>
        <rotation rank="2" dims="3 3" order="F">
          0.000000000000000e0 1.000000000000000e0 0.000000000000000e0
          1.000000000000000e0 0.000000000000000e0 0.000000000000000e0
          -1.000000000000000e0 -1.000000000000000e0 -1.000000000000000e0
          </rotation>
        <fractional_translation>0.000000000000000e0 0.000000000000000e0 0.000000000000000e0</fractional_translation>
        <equivalent_atoms nat="2" size="2">1 2</equivalent_atoms>
      </symmetry>
      <symmetry>
        <info name="180 deg rotation - cart. axis [0,1,0]">crystal_symmetry</info>
        <rotation rank="2" dims="3 3" order="F">
          0.000000000000000e0 0.000000000000000e0 1.000000000000000e0
          -1.000000000000000e0 -1.000000000000000e0 -1.000000000000000e0
          1.000000000000000e0 0.000000000000000e0 0.000000000000000e0
          </rotation>
        <fractional_translation>0.000000000000000e0 0.000000000000000e0 0.000000000000000e0</fractional_translation>
        <equivalent_atoms nat="2" size="2">1 2</equivalent_atoms>
      </symmetry>
      <symmetry>
        <info name="180 deg rotation - cart. axis [1,0,0]">crystal_symmetry</info>
        <rotation rank="2" dims="3 3" order="F">
          -1.000000000000000e0 -1.000000000000000e0 -1.000000000000000e0
          0.000000000000000e0 0.000000000000000e0 1.000000000000000e0
          0.000000000000000e0 1.000000000000000e0 0.000000000000000e0
          </rotation>
        <fractional_translation>0.000000000000000e0 0.000000000000000e0 0.000000000000000e0</fractional_translation>
        <equivalent_atoms nat="2" size="2">1 2</equivalent_atoms>
      </symmetry>
      <symmetry>
        <info name="180 deg rotation - cart. axis [1,1,0]">crystal_symmetry</info>
        <rotation rank="2" dims="3 3" order="F">
          -1.000000000000000e0 0.000000000000000e0 0.000000000000000e0
          0.000000000000000e0 -1.000000000000000e0 0.000000000000000e0
          1.000000000000000e0 1.000000000000000e0 1.000000000000000e0
          </rotation>
        <fractional_translation>-2.500000000000000e-1 -2.500000000000000e-1 -2.499999999999998e-1</fractional_translation>
        <equivalent_atoms nat="2" size="2">2 1</equivalent_atoms>
      </symmetry>
      <symmetry>
        <info name="180 deg rotation - cart. axis [1,-1,0]">crystal_symmetry</info>
        <rotation rank="2" dims="3 3" order="F">
          0.000000000000000e0 -1.000000000000000e0 0.000000000000000e0
          -1.000000000000000e0 0.000000000000000e0 0.000000000000000e0
          0.000000000000000e0 0.000000000000000e0 -1.000000000000000e0
          </rotation>
        <fractional_translation>-2.500000000000000e-1 -2.500000000000000e-1 -2.500000000000000e-1</fractional_translation>
        <equivalent_atoms nat="2" size="2">2 1</equivalent_atoms>
      </symmetry>
      <symmetry>
        <info name=" 90 deg rotation - cart. axis [0,0,-1]">crystal_symmetry</info>
        <rotation rank="2" dims="3 3" order="F">
          0.000000000000000e0 0.000000000000000e0 -1.000000000000000e0
          1.000000000000000e0 1.000000000000000e0 1.000000000000000e0
          0.000000000000000e0 -1.000000000000000e0 0.000000000000000e0
          </rotation>
        <fractional_translation>-2.500000000000000e-1 -2.499999999999998e-1 -2.500000000000000e-1</fractional_translation>
        <equivalent_atoms nat="2" size="2">2 1</equivalent_atoms>
      </symmetry>
      <symmetry>
        <info name=" 90 deg rotation - cart. axis [0,0,1]">crystal_symmetry</info>
        <rotation rank="2" dims="3 3" order="F">
          1.000000000000000e0 1.000000000000000e0 1.000000000000000e0
          0.000000000000000e0 0.000000000000000e0 -1.000000000000000e0
          -1.000000000000000e0 0.000000000000000e0 0.000000000000000e0
          </rotation>
        <fractional_translation>-2.499999999999998e-1 -2.500000000000000e-1 -2.500000000000000e-1</fractional_translation>
        <equivalent_atoms nat="2" size="2">2 1</equivalent_atoms>
      </symmetry>
      <symmetry>
        <info name="180 deg rotation - cart. axis [1,0,1]">crystal_symmetry</info>
        <rotation rank="2" dims="3 3" order="F">
          -1.000000000000000e0 0.000000000000000e0 0.000000000000000e0
          1.000000000000000e0 1.000000000000000e0 1.000000000000000e0
          0.000000000000000e0 0.000000000000000e0 -1.000000000000000e0
          </rotation>
        <fractional_translation>-2.500000000000000e-1 -2.499999999999998e-1 -2.500000000000000e-1</fractional_translation>
        <equivalent_atoms nat="2" size="2">2 1</equivalent_atoms>
      </symmetry>
      <symmetry>
        <info name="180 deg rotation - cart. axis [-1,0,1]">crystal_symmetry</info>
        <rotation rank="2" dims="3 3" order="F">
          0.000000000000000e0 0.000000000000000e0 -1.000000000000000e0
          0.000000000000000e0 -1.000000000000000e0 0.000000000000000e0
          -1.000000000000000e0 0.000000000000000e0 0.000000000000000e0
          </rotation>
        <fractional_translation>-2.500000000000000e-1 -2.500000000000000e-1 -2.500000000000000e-1</fractional_translation>
        <equivalent_atoms nat="2" size="2">2 1</equivalent_atoms>
      </symmetry>
      <symmetry>
        <info name=" 90 deg rotation - cart. axis [0,1,0]">crystal_symmetry</info>
        <rotation rank="2" dims="3 3" order="F">
          0.000000000000000e0 -1.000000000000000e0 0.000000000000000e0
          0.000000000000000e0 0.000000000000000e0 -1.000000000000000e0
          1.000000000000000e0 1.000000000000000e0 1.000000000000000e0
          </rotation>
        <fractional_translation>-2.500000000000000e-1 -2.500000000000000e-1 -2.499999999999998e-1</fractional_translation>
        <equivalent_atoms nat="2" size="2">2 1</equivalent_atoms>
      </symmetry>
      <symmetry>
        <info name=" 90 deg rotation - cart. axis [0,-1,0]">crystal_symmetry</info>
        <rotation rank="2" dims="3 3" order="F">
          1.000000000000000e0 1.000000000000000e0 1.000000000000000e0
          -1.000000000000000e0 0.000000000000000e0 0.000000000000000e0
          0.000000000000000e0 -1.000000000000000e0 0.000000000000000e0
          </rotation>
        <fractional_translation>-2.499999999999998e-1 -2.500000000000000e-1 -2.500000000000000e-1</fractional_translation>
        <equivalent_atoms nat="2" size="2">2 1</equivalent_atoms>
      </symmetry>
      <symmetry>
        <info name="180 deg rotation - cart. axis [0,1,1]">crystal_symmetry</info>
        <rotation rank="2" dims="3 3" order="F">
          1.000000000000000e0 1.000000000000000e0 1.000000000000000e0
          0.000000000000000e0 -1.000000000000000e0 0.000000000000000e0
          0.000000000000000e0 0.000000000000000e0 -1.000000000000000e0
          </rotation>
        <fractional_translation>-2.499999999999998e-1 -2.500000000000000e-1 -2.500000000000000e-1</fractional_translation>
        <equivalent_atoms nat="2" size="2">2 1</equivalent_atoms>
      </symmetry>
      <symmetry>
        <info name="180 deg rotation - cart. axis [0,1,-1]">crystal_symmetry</info>
        <rotation rank="2" dims="3 3" order="F">
          -1.000000000000000e0 0.000000000000000e0 0.000000000000000e0
          0.000000000000000e0 0.000000000000000e0 -1.000000000000000e0
          0.000000000000000e0 -1.000000000000000e0 0.000000000000000e0
          </rotation>
        <fractional_translation>-2.500000000000000e-1 -2.500000000000000e-1 -2.500000000000000e-1</fractional_translation>
        <equivalent_atoms nat="2" size="2">2 1</equivalent_atoms>
      </symmetry>
      <symmetry>
        <info name=" 90 deg rotation - cart. axis [-1,0,0]">crystal_symmetry</info>
        <rotation rank="2" dims="3 3" order="F">
          0.000000000000000e0 0.000000000000000e0 -1.000000000000000e0
          -1.000000000000000e0 0.000000000000000e0 0.000000000000000e0
          1.000000000000000e0 1.000000000000000e0 1.000000000000000e0
          </rotation>
        <fractional_translation>-2.500000000000000e-1 -2.500000000000000e-1 -2.499999999999998e-1</fractional_translation>
        <equivalent_atoms nat="2" size="2">2 1</equivalent_atoms>
      </symmetry>
      <symmetry>
        <info name=" 90 deg rotation - cart. axis [1,0,0]">crystal_symmetry</info>
        <rotation rank="2" dims="3 3" order="F">
          0.000000000000000e0 -1.000000000000000e0 0.000000000000000e0
          1.000000000000000e0 1.000000000000000e0 1.000000000000000e0
          -1.000000000000000e0 0.000000000000000e0 0.000000000000000e0
          </rotation>
        <fractional_translation>-2.500000000000000e-1 -2.499999999999998e-1 -2.500000000000000e-1</fractional_translation>
        <equivalent_atoms nat="2" size="2">2 1</equivalent_atoms>
      </symmetry>
      <symmetry>
        <info name="120 deg rotation - cart. axis [-1,-1,-1]">crystal_symmetry</info>
        <rotation rank="2" dims="3 3" order="F">
          0.000000000000000e0 1.000000000000000e0 0.000000000000000e0
          0.000000000000000e0 0.000000000000000e0 1.000000000000000e0
          1.000000000000000e0 0.000000000000000e0 0.000000000000000e0
          </rotation>
        <fractional_translation>0.000000000000000e0 0.000000000000000e0 0.000000000000000e0</fractional_translation>
        <equivalent_atoms nat="2" size="2">1 2</equivalent_atoms>
      </symmetry>
      <symmetry>
        <info name="120 deg rotation - cart. axis [-1,1,1]">crystal_symmetry</info>
        <rotation rank="2" dims="3 3" order="F">
          1.000000000000000e0 0.000000000000000e0 0.000000000000000e0
          -1.000000000000000e0 -1.000000000000000e0 -1.000000000000000e0
          0.000000000000000e0 1.000000000000000e0 0.000000000000000e0
          </rotation>
        <fractional_translation>0.000000000000000e0 0.000000000000000e0 0.000000000000000e0</fractional_translation>
        <equivalent_atoms nat="2" size="2">1 2</equivalent_atoms>
      </symmetry>
      <symmetry>
        <info name="120 deg rotation - cart. axis [1,1,-1]">crystal_symmetry</info>
        <rotation rank="2" dims="3 3" order="F">
          -1.000000000000000e0 -1.000000000000000e0 -1.000000000000000e0
          1.000000000000000e0 0.000000000000000e0 0.000000000000000e0
          0.000000000000000e0 0.000000000000000e0 1.000000000000000e0
          </rotation>
        <fractional_translation>0.000000000000000e0 0.000000000000000e0 0.000000000000000e0</fractional_translation>
        <equivalent_atoms nat="2" size="2">1 2</equivalent_atoms>
      </symmetry>
      <symmetry>
        <info name="120 deg rotation - cart. axis [1,-1,1]">crystal_symmetry</info>
        <rotation rank="2" dims="3 3" order="F">
          0.000000000000000e0 0.000000000000000e0 1.000000000000000e0
          0.000000000000000e0 1.000000000000000e0 0.000000000000000e0
          -1.000000000000000e0 -1.000000000000000e0 -1.000000000000000e0
          </rotation>
        <fractional_translation>0.000000000000000e0 0.000000000000000e0 0.000000000000000e0</fractional_translation>
        <equivalent_atoms nat="2" size="2">1 2</equivalent_atoms>
      </symmetry>
      <symmetry>
        <info name="120 deg rotation - cart. axis [1,1,1]">crystal_symmetry</info>
        <rotation rank="2" dims="3 3" order="F">
          0.000000000000000e0 0.000000000000000e0 1.000000000000000e0
          1.000000000000000e0 0.000000000000000e0 0.000000000000000e0
          0.000000000000000e0 1.000000000000000e0 0.000000000000000e0
          </rotation>
        <fractional_translation>0.000000000000000e0 0.000000000000000e0 0.000000000000000e0</fractional_translation>
        <equivalent_atoms nat="2" size="2">1 2</equivalent_atoms>
      </symmetry>
      <symmetry>
        <info name="120 deg rotation - cart. axis [-1,1,-1]">crystal_symmetry</info>
        <rotation rank="2" dims="3 3" order="F">
          -1.000000000000000e0 -1.000000000000000e0 -1.000000000000000e0
          0.000000000000000e0 1.000000000000000e0 0.000000000000000e0
          1.000000000000000e0 0.000000000000000e0 0.000000000000000e0
          </rotation>
        <fractional_translation>0.000000000000000e0 0.000000000000000e0 0.000000000000000e0</fractional_translation>
        <equivalent_atoms nat="2" size="2">1 2</equivalent_atoms>
      </symmetry>
      <symmetry>
        <info name="120 deg rotation - cart. axis [1,-1,-1]">crystal_symmetry</info>
        <rotation rank="2" dims="3 3" order="F">
          1.000000000000000e0 0.000000000000000e0 0.000000000000000e0
          0.000000000000000e0 0.000000000000000e0 1.000000000000000e0
          -1.000000000000000e0 -1.000000000000000e0 -1.000000000000000e0
          </rotation>
        <fractional_translation>0.000000000000000e0 0.000000000000000e0 0.000000000000000e0</fractional_translation>
        <equivalent_atoms nat="2" size="2">1 2</equivalent_atoms>
      </symmetry>
      <symmetry>
        <info name="120 deg rotation - cart. axis [-1,-1,1]">crystal_symmetry</info>
        <rotation rank="2" dims="3 3" order="F">
          0.000000000000000e0 1.000000000000000e0 0.000000000000000e0
          -1.000000000000000e0 -1.000000000000000e0 -1.000000000000000e0
          0.000000000000000e0 0.000000000000000e0 1.000000000000000e0
          </rotation>
        <fractional_translation>0.000000000000000e0 0.000000000000000e0 0.000000000000000e0</fractional_translation>
        <equivalent_atoms nat="2" size="2">1 2</equivalent_atoms>
      </symmetry>
      <symmetry>
        <info name="inversion">crystal_symmetry</info>
        <rotation rank="2" dims="3 3" order="F">
          -1.000000000000000e0 0.000000000000000e0 0.000000000000000e0
          0.000000000000000e0 -1.000000000000000e0 0.000000000000000e0
          0.000000000000000e0 0.000000000000000e0 -1.000000000000000e0
          </rotation>
        <fractional_translation>-2.500000000000000e-1 -2.500000000000000e-1 -2.500000000000000e-1</fractional_translation>
        <equivalent_atoms nat="2" size="2">2 1</equivalent_atoms>
      </symmetry>
      <symmetry>
        <info name="inv. 180 deg rotation - cart. axis [0,0,1]">crystal_symmetry</info>
        <rotation rank="2" dims="3 3" order="F">
          0.000000000000000e0 -1.000000000000000e0 0.000000000000000e0
          -1.000000000000000e0 0.000000000000000e0 0.000000000000000e0
          1.000000000000000e0 1.000000000000000e0 1.000000000000000e0
          </rotation>
        <fractional_translation>-2.500000000000000e-1 -2.500000000000000e-1 -2.499999999999998e-1</fractional_translation>
        <equivalent_atoms nat="2" size="2">2 1</equivalent_atoms>
      </symmetry>
      <symmetry>
        <info name="inv. 180 deg rotation - cart. axis [0,1,0]">crystal_symmetry</info>
        <rotation rank="2" dims="3 3" order="F">
          0.000000000000000e0 0.000000000000000e0 -1.000000000000000e0
          1.000000000000000e0 1.000000000000000e0 1.000000000000000e0
          -1.000000000000000e0 0.000000000000000e0 0.000000000000000e0
          </rotation>
        <fractional_translation>-2.500000000000000e-1 -2.499999999999998e-1 -2.500000000000000e-1</fractional_translation>
        <equivalent_atoms nat="2" size="2">2 1</equivalent_atoms>
      </symmetry>
      <symmetry>
        <info name="inv. 180 deg rotation - cart. axis [1,0,0]">crystal_symmetry</info>
        <rotation rank="2" dims="3 3" order="F">
          1.000000000000000e0 1.000000000000000e0 1.000000000000000e0
          0.000000000000000e0 0.000000000000000e0 -1.000000000000000e0
          0.000000000000000e0 -1.000000000000000e0 0.000000000000000e0
          </rotation>
        <fractional_translation>-2.499999999999998e-1 -2.500000000000000e-1 -2.500000000000000e-1</fractional_translation>
        <equivalent_atoms nat="2" size="2">2 1</equivalent_atoms>
      </symmetry>
      <symmetry>
        <info name="inv. 180 deg rotation - cart. axis [1,1,0]">crystal_symmetry</info>
        <rotation rank="2" dims="3 3" order="F">
          1.000000000000000e0 0.000000000000000e0 0.000000000000000e0
          0.000000000000000e0 1.000000000000000e0 0.000000000000000e0
          -1.000000000000000e0 -1.000000000000000e0 -1.000000000000000e0
          </rotation>
        <fractional_translation>0.000000000000000e0 0.000000000000000e0 0.000000000000000e0</fractional_translation>
        <equivalent_atoms nat="2" size="2">1 2</equivalent_atoms>
      </symmetry>
      <symmetry>
        <info name="inv. 180 deg rotation - cart. axis [1,-1,0]">crystal_symmetry</info>
        <rotation rank="2" dims="3 3" order="F">
          0.000000000000000e0 1.000000000000000e0 0.000000000000000e0
          1.000000000000000e0 0.000000000000000e0 0.000000000000000e0
          0.000000000000000e0 0.000000000000000e0 1.000000000000000e0
          </rotation>
        <fractional_translation>0.000000000000000e0 0.000000000000000e0 0.000000000000000e0</fractional_translation>
        <equivalent_atoms nat="2" size="2">1 2</equivalent_atoms>
      </symmetry>
      <symmetry>
        <info name="inv.  90 deg rotation - cart. axis [0,0,-1]">crystal_symmetry</info>
        <rotation rank="2" dims="3 3" order="F">
          0.000000000000000e0 0.000000000000000e0 1.000000000000000e0
          -1.000000000000000e0 -1.000000000000000e0 -1.000000000000000e0
          0.000000000000000e0 1.000000000000000e0 0.000000000000000e0
          </rotation>
        <fractional_translation>0.000000000000000e0 0.000000000000000e0 0.000000000000000e0</fractional_translation>
        <equivalent_atoms nat="2" size="2">1 2</equivalent_atoms>
      </symmetry>
      <symmetry>
        <info name="inv.  90 deg rotation - cart. axis [0,0,1]">crystal_symmetry</info>
        <rotation rank="2" dims="3 3" order="F">
          -1.000000000000000e0 -1.000000000000000e0 -1.000000000000000e0
          0.000000000000000e0 0.000000000000000e0 1.000000000000000e0
          1.000000000000000e0 0.000000000000000e0 0.000000000000000e0
          </rotation>
        <fractional_translation>0.000000000000000e0 0.000000000000000e0 0.000000000000000e0</fractional_translation>
        <equivalent_atoms nat="2" size="2">1 2</equivalent_atoms>
      </symmetry>
      <symmetry>
        <info name="inv. 180 deg rotation - cart. axis [1,0,1]">crystal_symmetry</info>
        <rotation rank="2" dims="3 3" order="F">
          1.000000000000000e0 0.000000000000000e0 0.000000000000000e0
          -1.000000000000000e0 -1.000000000000000e0 -1.000000000000000e0
          0.000000000000000e0 0.000000000000000e0 1.000000000000000e0
          </rotation>
        <fractional_translation>0.000000000000000e0 0.000000000000000e0 0.000000000000000e0</fractional_translation>
        <equivalent_atoms nat="2" size="2">1 2</equivalent_atoms>
      </symmetry>
      <symmetry>
        <info name="inv. 180 deg rotation - cart. axis [-1,0,1]">crystal_symmetry</info>
        <rotation rank="2" dims="3 3" order="F">
          0.000000000000000e0 0.000000000000000e0 1.000000000000000e0
          0.000000000000000e0 1.000000000000000e0 0.000000000000000e0
          1.000000000000000e0 0.000000000000000e0 0.000000000000000e0
          </rotation>
        <fractional_translation>0.000000000000000e0 0.000000000000000e0 0.000000000000000e0</fractional_translation>
        <equivalent_atoms nat="2" size="2">1 2</equivalent_atoms>
      </symmetry>
      <symmetry>
        <info name="inv.  90 deg rotation - cart. axis [0,1,0]">crystal_symmetry</info>
        <rotation rank="2" dims="3 3" order="F">
          0.000000000000000e0 1.000000000000000e0 0.000000000000000e0
          0.000000000000000e0 0.000000000000000e0 1.000000000000000e0
          -1.000000000000000e0 -1.000000000000000e0 -1.000000000000000e0
          </rotation>
        <fractional_translation>0.000000000000000e0 0.000000000000000e0 0.000000000000000e0</fractional_translation>
        <equivalent_atoms nat="2" size="2">1 2</equivalent_atoms>
      </symmetry>
      <symmetry>
        <info name="inv.  90 deg rotation - cart. axis [0,-1,0]">crystal_symmetry</info>
        <rotation rank="2" dims="3 3" order="F">
          -1.000000000000000e0 -1.000000000000000e0 -1.000000000000000e0
          1.000000000000000e0 0.000000000000000e0 0.000000000000000e0
          0.000000000000000e0 1.000000000000000e0 0.000000000000000e0
          </rotation>
        <fractional_translation>0.000000000000000e0 0.000000000000000e0 0.000000000000000e0</fractional_translation>
        <equivalent_atoms nat="2" size="2">1 2</equivalent_atoms>
      </symmetry>
      <symmetry>
        <info name="inv. 180 deg rotation - cart. axis [0,1,1]">crystal_symmetry</info>
        <rotation rank="2" dims="3 3" order="F">
          -1.000000000000000e0 -1.000000000000000e0 -1.000000000000000e0
          0.000000000000000e0 1.000000000000000e0 0.000000000000000e0
          0.000000000000000e0 0.000000000000000e0 1.000000000000000e0
          </rotation>
        <fractional_translation>0.000000000000000e0 0.000000000000000e0 0.000000000000000e0</fractional_translation>
        <equivalent_atoms nat="2" size="2">1 2</equivalent_atoms>
      </symmetry>
      <symmetry>
        <info name="inv. 180 deg rotation - cart. axis [0,1,-1]">crystal_symmetry</info>
        <rotation rank="2" dims="3 3" order="F">
          1.000000000000000e0 0.000000000000000e0 0.000000000000000e0
          0.000000000000000e0 0.000000000000000e0 1.000000000000000e0
          0.000000000000000e0 1.000000000000000e0 0.000000000000000e0
          </rotation>
        <fractional_translation>0.000000000000000e0 0.000000000000000e0 0.000000000000000e0</fractional_translation>
        <equivalent_atoms nat="2" size="2">1 2</equivalent_atoms>
      </symmetry>
      <symmetry>
        <info name="inv.  90 deg rotation - cart. axis [-1,0,0]">crystal_symmetry</info>
        <rotation rank="2" dims="3 3" order="F">
          0.000000000000000e0 0.000000000000000e0 1.000000000000000e0
          1.000000000000000e0 0.000000000000000e0 0.000000000000000e0
          -1.000000000000000e0 -1.000000000000000e0 -1.000000000000000e0
          </rotation>
        <fractional_translation>0.000000000000000e0 0.000000000000000e0 0.000000000000000e0</fractional_translation>
        <equivalent_atoms nat="2" size="2">1 2</equivalent_atoms>
      </symmetry>
      <symmetry>
        <info name="inv.  90 deg rotation - cart. axis [1,0,0]">crystal_symmetry</info>
        <rotation rank="2" dims="3 3" order="F">
          0.000000000000000e0 1.000000000000000e0 0.000000000000000e0
          -1.000000000000000e0 -1.000000000000000e0 -1.000000000000000e0
          1.000000000000000e0 0.000000000000000e0 0.000000000000000e0
          </rotation>
        <fractional_translation>0.000000000000000e0 0.000000000000000e0 0.000000000000000e0</fractional_translation>
        <equivalent_atoms nat="2" size="2">1 2</equivalent_atoms>
      </symmetry>
      <symmetry>
        <info name="inv. 120 deg rotation - cart. axis [-1,-1,-1]">crystal_symmetry</info>
        <rotation rank="2" dims="3 3" order="F">
          0.000000000000000e0 -1.000000000000000e0 0.000000000000000e0
          0.000000000000000e0 0.000000000000000e0 -1.000000000000000e0
          -1.000000000000000e0 0.000000000000000e0 0.000000000000000e0
          </rotation>
        <fractional_translation>-2.500000000000000e-1 -2.500000000000000e-1 -2.500000000000000e-1</fractional_translation>
        <equivalent_atoms nat="2" size="2">2 1</equivalent_atoms>
      </symmetry>
      <symmetry>
        <info name="inv. 120 deg rotation - cart. axis [-1,1,1]">crystal_symmetry</info>
        <rotation rank="2" dims="3 3" order="F">
          -1.000000000000000e0 0.000000000000000e0 0.000000000000000e0
          1.000000000000000e0 1.000000000000000e0 1.000000000000000e0
          0.000000000000000e0 -1.000000000000000e0 0.000000000000000e0
          </rotation>
        <fractional_translation>-2.500000000000000e-1 -2.499999999999998e-1 -2.500000000000000e-1</fractional_translation>
        <equivalent_atoms nat="2" size="2">2 1</equivalent_atoms>
      </symmetry>
      <symmetry>
        <info name="inv. 120 deg rotation - cart. axis [1,1,-1]">crystal_symmetry</info>
        <rotation rank="2" dims="3 3" order="F">
          1.000000000000000e0 1.000000000000000e0 1.000000000000000e0
          -1.000000000000000e0 0.000000000000000e0 0.000000000000000e0
          0.000000000000000e0 0.000000000000000e0 -1.000000000000000e0
          </rotation>
        <fractional_translation>-2.499999999999998e-1 -2.500000000000000e-1 -2.500000000000000e-1</fractional_translation>
        <equivalent_atoms nat="2" size="2">2 1</equivalent_atoms>
      </symmetry>
      <symmetry>
        <info name="inv. 120 deg rotation - cart. axis [1,-1,1]">crystal_symmetry</info>
        <rotation rank="2" dims="3 3" order="F">
          0.000000000000000e0 0.000000000000000e0 -1.000000000000000e0
          0.000000000000000e0 -1.000000000000000e0 0.000000000000000e0
          1.000000000000000e0 1.000000000000000e0 1.000000000000000e0
          </rotation>
        <fractional_translation>-2.500000000000000e-1 -2.500000000000000e-1 -2.499999999999998e-1</fractional_translation>
        <equivalent_atoms nat="2" size="2">2 1</equivalent_atoms>
      </symmetry>
      <symmetry>
        <info name="inv. 120 deg rotation - cart. axis [1,1,1]">crystal_symmetry</info>
        <rotation rank="2" dims="3 3" order="F">
          0.000000000000000e0 0.000000000000000e0 -1.000000000000000e0
          -1.000000000000000e0 0.000000000000000e0 0.000000000000000e0
          0.000000000000000e0 -1.000000000000000e0 0.000000000000000e0
          </rotation>
        <fractional_translation>-2.500000000000000e-1 -2.500000000000000e-1 -2.500000000000000e-1</fractional_translation>
        <equivalent_atoms nat="2" size="2">2 1</equivalent_atoms>
      </symmetry>
      <symmetry>
        <info name="inv. 120 deg rotation - cart. axis [-1,1,-1]">crystal_symmetry</info>
        <rotation rank="2" dims="3 3" order="F">
          1.000000000000000e0 1.000000000000000e0 1.000000000000000e0
          0.000000000000000e0 -1.000000000000000e0 0.000000000000000e0
          -1.000000000000000e0 0.000000000000000e0 0.000000000000000e0
          </rotation>
        <fractional_translation>-2.499999999999998e-1 -2.500000000000000e-1 -2.500000000000000e-1</fractional_translation>
        <equivalent_atoms nat="2" size="2">2 1</equivalent_atoms>
      </symmetry>
      <symmetry>
        <info name="inv. 120 deg rotation - cart. axis [1,-1,-1]">crystal_symmetry</info>
        <rotation rank="2" dims="3 3" order="F">
          -1.000000000000000e0 0.000000000000000e0 0.000000000000000e0
          0.000000000000000e0 0.000000000000000e0 -1.000000000000000e0
          1.000000000000000e0 1.000000000000000e0 1.000000000000000e0
          </rotation>
        <fractional_translation>-2.500000000000000e-1 -2.500000000000000e-1 -2.499999999999998e-1</fractional_translation>
        <equivalent_atoms nat="2" size="2">2 1</equivalent_atoms>
      </symmetry>
      <symmetry>
        <info name="inv. 120 deg rotation - cart. axis [-1,-1,1]">crystal_symmetry</info>
        <rotation rank="2" dims="3 3" order="F">
          0.000000000000000e0 -1.000000000000000e0 0.000000000000000e0
          1.000000000000000e0 1.000000000000000e0 1.000000000000000e0
          0.000000000000000e0 0.000000000000000e0 -1.000000000000000e0
          </rotation>
        <fractional_translation>-2.500000000000000e-1 -2.499999999999998e-1 -2.500000000000000e-1</fractional_translation>
        <equivalent_atoms nat="2" size="2">2 1</equivalent_atoms>
      </symmetry>
    </symmetries>
    <basis_set>
      <gamma_only>false</gamma_only>
      <ecutwfc>2.000000000000000e1</ecutwfc>
      <ecutrho>8.000000000000000e1</ecutrho>
      <fft_grid nr1="32" nr2="32" nr3="32"/>
      <fft_smooth nr1="32" nr2="32" nr3="32"/>
      <ngm>10777</ngm>
      <ngms>10777</ngms>
      <npwx>1363</npwx>
      <reciprocal_lattice>
        <b1>-1.757469244288225e-1 1.757469244288225e-1 1.757469244288225e-1</b1>
        <b2>1.757469244288225e-1 -1.757469244288225e-1 1.757469244288225e-1</b2>
        <b3>1.757469244288225e-1 1.757469244288225e-1 -1.757469244288225e-1</b3>
      </reciprocal_lattice>
    </basis_set>
    <dft>
      <functional>PBE</functional>
      <dftU>
        <lda_plus_u_kind>0</lda_plus_u_kind>
        <Hubbard_U specie="Ge" label="4p">1.175978412713844e-1</Hubbard_U>
        <Hubbard_J0 specie="Ge" label="4p">0.000000000000000e0</Hubbard_J0>
        <Hubbard_alpha specie="Ge" label="4p">0.000000000000000e0</Hubbard_alpha>
        <Hubbard_beta specie="Ge" label="4p">0.000000000000000e0</Hubbard_beta>
        <Hubbard_J specie="Ge" label="4p">0.000000000000000e0 0.000000000000000e0 0.000000000000000e0</Hubbard_J>
        <Hubbard_ns specie="Ge" label="4p" spin="1" index="1" rank="2" dims="3 3" order="F">
          7.899837762198963e-1 -9.975274520784872e-16 2.887962318520789e-16
          -9.975274520784872e-16 7.899837762198959e-1 -4.865977296438146e-16
          2.887962318520789e-16 -4.865977296438146e-16 7.899837762198963e-1
          </Hubbard_ns>
        <Hubbard_ns specie="Ge" label="4p" spin="1" index="2" rank="2" dims="3 3" order="F">
          7.899837762198962e-1 -9.949253958975779e-16 2.913982888034846e-16
          -9.949253958975779e-16 7.899837762198960e-1 -4.883324737629627e-16
          2.913982888034846e-16 -4.883324737629627e-16 7.899837762198962e-1
          </Hubbard_ns>
        <U_projection_type>atomic</U_projection_type>
      </dftU>
    </dft>
    <magnetization>
      <lsda>false</lsda>
      <noncolin>false</noncolin>
      <spinorbit>false</spinorbit>
      <total>0.000000000000000e0</total>
      <absolute>0.000000000000000e0</absolute>
      <do_magnetization>false</do_magnetization>
    </magnetization>
    <total_energy>
      <etot>-1.640585918712279e2</etot>
      <eband>-1.640585918712279e2</eband>
      <ehart>5.724994639998702e-1</ehart>
      <vtxc>-3.416757855490920e0</vtxc>
      <etxc>-6.615246673904700e0</etxc>
      <ewald>-8.015664697348324e0</ewald>
      <demet>-6.991932786936865e-5</demet>
    </total_energy>
    <band_structure>
      <lsda>false</lsda>
      <noncolin>false</noncolin>
      <spinorbit>false</spinorbit>
      <nbnd>7</nbnd>
      <nelec>8.000000000000000e0</nelec>
      <num_of_atomic_wfc>8</num_of_atomic_wfc>
      <wf_collected>false</wf_collected>
      <fermi_energy>1.973766154643973e-1</fermi_energy>
      <starting_k_points>
        <monkhorst_pack nk1="12" nk2="12" nk3="12" k1="0" k2="0" k3="0">Monkhorst-Pack</monkhorst_pack>
      </starting_k_points>
      <nks>72</nks>
      <occupations_kind>smearing</occupations_kind>
      <smearing degauss="7.000000000000e-3">fd</smearing>
      <ks_energies>
        <k_point weight="1.157407407407e-3">0.000000000000000e0 0.000000000000000e0 0.000000000000000e0</k_point>
        <npw>1363</npw>
        <eigenvalues size="7">-2.583951973801132e-1 1.942157794628113e-1 1.942157813410147e-1 1.942161614639581e-1 2.032199910354609e-1 2.930114950592757e-1 2.930115277865319e-1</eigenvalues>
        <occupations size="7">1.000000000000000e0 7.115853159122823e-1 7.115852057789044e-1 7.115629157586714e-1 1.584860682395870e-1 1.359028088015001e-12 1.359015380285684e-12</occupations>
      </ks_energies>
      <ks_energies>
        <k_point weight="9.259259259259e-3">1.464557703573521e-2 1.464557703573521e-2 -1.464557703573521e-2</k_point>
        <npw>1339</npw>
        <eigenvalues size="7">-2.589944674835602e-1 1.400893926054939e-1 1.879442771206232e-1 1.879442781641309e-1 2.346437764659488e-1 3.013324036642669e-1 3.013324975349815e-1</eigenvalues>
        <occupations size="7">1.000000000000000e0 9.999999220951821e-1 9.367282224811840e-1 9.367282048105825e-1 2.375341995227929e-5 1.261059748286911e-13 1.261025926860566e-13</occupations>
      </ks_energies>
      <ks_energies>
        <k_point weight="9.259259259259e-3">2.929115407147042e-2 2.929115407147042e-2 -2.929115407147042e-2</k_point>
        <npw>1330</npw>
        <eigenvalues size="7">-2.586522317213638e-1 7.764847544281553e-2 1.745142733289693e-1 1.745142746461326e-1 2.332365241029001e-1 3.189185806779693e-1 3.189200266113776e-1</eigenvalues>
        <occupations size="7">1.000000000000000e0 9.999999999999986e-1 9.985461682800993e-1 9.985461677337709e-1 3.550902416044465e-5 8.290296318506551e-16 8.286872106892128e-16</occupations>
      </ks_energies>
      <ks_energies>
        <k_point weight="9.259259259259e-3">4.393673110720563e-2 4.393673110720563e-2 -4.393673110720563e-2</k_point>
        <npw>1332</npw>
        <eigenvalues size="7">-2.524943144930852e-1 1.621083394193927e-2 1.607938781099151e-1 1.607938945405667e-1 2.211505788523557e-1 3.336354799921452e-1 3.336356635837912e-1</eigenvalues>
        <occupations size="7">1.000000000000000e0 1.000000000000000e0 9.999711164854570e-1 9.999711163498677e-1 1.120833773100376e-3 1.237189692045006e-17 1.237124797263582e-17</occupations>
      </ks_energies>
      <ks_energies>
        <k_point weight="9.259259259259e-3">5.858230814294084e-2 5.858230814294084e-2 -5.858230814294084e-2</k_point>
        <npw>1326</npw>
        <eigenvalues size="7">-2.364801259544716e-1 -4.164653783822518e-2 1.499314082702801e-1 1.499314094063876e-1 2.102151727147436e-1 3.393060300499523e-1 3.393062297547266e-1</eigenvalues>
        <occupations size="7">1.000000000000000e0 1.000000000000000e0 9.999987034125464e-1 9.999987034121254e-1 2.488817867119470e-2 2.447997549759256e-18 2.447857874658921e-18</occupations>
      </ks_energies>
      <ks_energies>
        <k_point weight="9.259259259259e-3">7.322788517867606e-2 7.322788517867606e-2 -7.322788517867606e-2</k_point>
        <npw>1326</npw>
        <eigenvalues size="7">-2.114221531019372e-1 -9.202389516068765e-2 1.431275078212016e-1 1.431275091332309e-1 2.031986089531355e-1 3.391162365428735e-1 3.391162834605463e-1</eigenvalues>
        <occupations size="7">1.000000000000000e0 1.000000000000000e0 9.999998144135875e-1 9.999998144135175e-1 1.593025378879509e-1 2.584409581268820e-18 2.584374937362948e-18</occupations>
      </ks_energies>
      <ks_energies>
        <k_point weight="4.629629629630e-3">-8.787346221441126e-2 -8.787346221441126e-2 8.787346221441126e-2</k_point>
        <npw>1350</npw>
        <eigenvalues size="7">-1.935793605731735e-1 -1.182375098965140e-1 1.408227122129036e-1 1.408227133251057e-1 2.008135449533347e-1 3.383947619004859e-1 3.383948063281556e-1</eigenvalues>
        <occupations size="7">1.000000000000000e0 1.000000000000000e0 9.999999039366692e-1 9.999999039366388e-1 2.724991140416990e-1 3.176032232651824e-18 3.175991917561631e-18</occupations>
      </ks_energies>
      <ks_energies>
        <k_point weight="6.944444444444e-3">2.929115407147042e-2 0.000000000000000e0 0.000000000000000e0</k_point>
        <npw>1331</npw>
        <eigenvalues size="7">-2.591263058912649e-1 1.389790923401991e-1 1.765264846700497e-1 1.765265125315831e-1 2.565436951002061e-1 2.799249112006620e-1 3.157807461089442e-1</eigenvalues>
        <occupations size="7">1.000000000000000e0 9.999999432724957e-1 9.974194793108941e-1 9.974194588217472e-1 4.553065773676171e-8 5.715653675715576e-11 2.032008641030794e-15</occupations>
      </ks_energies>
      <ks_energies>
        <k_point weight="2.777777777778e-2">4.393673110720563e-2 1.464557703573521e-2 -1.464557703573521e-2</k_point>
        <npw>1333</npw>
        <eigenvalues size="7">-2.588986872405208e-1 9.225218174357602e-2 1.612728178154972e-1 1.641281644643367e-1 2.656148580028176e-1 2.838252098994234e-1 3.369458207365156e-1</eigenvalues>
        <occupations size="7">1.000000000000000e0 9.999999999999096e-1 9.999668810150432e-1 9.999251206428386e-1 3.409702718855253e-9 1.875429336933306e-11 4.804802227563839e-18</occupations>
      </ks_energies>
      <ks_energies>
        <k_point weight="2.777777777778e-2">5.858230814294084e-2 2.929115407147042e-2 -2.929115407147042e-2</k_point>
        <npw>1338</npw>
        <eigenvalues size="7">-2.543176375178647e-1 3.472571356542995e-2 1.476751056078300e-1 1.480784038603691e-1 2.551959438592881e-1 3.047785978025296e-1 3.540675281862460e-1</eigenvalues>
        <occupations size="7">1.000000000000000e0 1.000000000000000e0 9.999993194959533e-1 9.999992363865100e-1 6.691730860430023e-8 4.711049155588381e-14 3.606975659025443e-20</occupations>
      </ks_energies>
      <ks_energies>
        <k_point weight="2.777777777778e-2">7.322788517867604e-2 4.393673110720563e-2 -4.393673110720563e-2</k_point>
        <npw>1332</npw>
        <eigenvalues size="7">-2.410286006000942e-1 -2.242612711310558e-2 1.322032268411207e-1 1.381353106811851e-1 2.436248382728179e-1 3.215851870047302e-1 3.599749581341503e-1</eigenvalues>
        <occupations size="7">1.000000000000000e0 1.000000000000000e0 9.999999918150456e-1 9.999999554247527e-1 1.825275231463519e-6 3.869782061765778e-16 6.669985050761042e-21</occupations>
      </ks_energies>
      <ks_energies>
        <k_point weight="2.777777777778e-2">8.787346221441126e-2 5.858230814294084e-2 -5.858230814294084e-2</k_point>
        <npw>1329</npw>
        <eigenvalues size="7">-2.180078387205770e-1 -7.472334864020986e-2 1.195890499205842e-1 1.335751426528783e-1 2.348706244103734e-1 3.286649501674422e-1 3.568315010957650e-1</eigenvalues>
        <occupations size="7">1.000000000000000e0 1.000000000000000e0 9.999999997772607e-1 9.999999878870685e-1 2.226273735955911e-5 5.119177638139884e-17 1.637487587034480e-20</occupations>
      </ks_energies>
      <ks_energies>
        <k_point weight="2.777777777778e-2">-7.322788517867604e-2 -1.025190392501465e-1 1.025190392501465e-1</k_point>
        <npw>1331</npw>
        <eigenvalues size="7">-1.940504816084400e-1 -1.119149368629126e-1 1.114173610612166e-1 1.342001100046138e-1 2.302569121188212e-1 3.324140107958600e-1 3.510252445449904e-1</eigenvalues>
        <occupations size="7">1.000000000000000e0 1.000000000000000e0 9.999999999784315e-1 9.999999855190254e-1 8.318415605452106e-5 1.753885529104919e-17 8.602850063928216e-20</occupations>
      </ks_energies>
      <ks_energies>
        <k_point weight="2.777777777778e-2">-5.858230814294084e-2 -8.787346221441126e-2 8.787346221441126e-2</k_point>
        <npw>1331</npw>
        <eigenvalues size="7">-2.006228863244117e-1 -1.026278850211337e-1 1.083053286722676e-1 1.397815447218575e-1 2.301980379841015e-1 3.374325993014638e-1 3.459601681844207e-1</eigenvalues>
        <occupations size="7">1.000000000000000e0 1.000000000000000e0 9.999999999911353e-1 9.999999286547144e-1 8.459512729051189e-5 4.180940795366124e-18 3.657109687608329e-19</occupations>
      </ks_energies>
      <ks_energies>
        <k_point weight="2.777777777778e-2">-4.393673110720563e-2 -7.322788517867606e-2 7.322788517867606e-2</k_point>
        <npw>1330</npw>
        <eigenvalues size="7">-2.265566230412030e-1 -5.799477388326793e-2 1.107206793877457e-1 1.497309108297694e-1 2.346375144704069e-1 3.410010425255232e-1 3.431950310290498e-1</eigenvalues>
        <occupations size="7">1.000000000000000e0 1.000000000000000e0 9.999999999823244e-1 9.999987756000753e-1 2.379595521183174e-5 1.508296826853305e-18 8.058378195586247e-19</occupations>
      </ks_energies>
      <ks_energies>
        <k_point weight="2.777777777778e-2">-2.929115407147042e-2 -5.858230814294084e-2 5.858230814294084e-2</k_point>
        <npw>1343</npw>
        <eigenvalues size="7">-2.465680635203223e-1 -3.576987806837267e-3 1.190992036082639e-1 1.629664278831840e-1 2.428997777197612e-1 3.321269662800634e-1 3.430379438981010e-1</eigenvalues>
        <occupations size="7">1.000000000000000e0 1.000000000000000e0 9.999999998063512e-1 9.999462698304521e-1 2.245415372638093e-6 1.903789451104329e-17 8.428293816286519e-19</occupations>
      </ks_energies>
      <ks_energies>
        <k_point weight="2.777777777778e-2">-1.464557703573520e-2 -4.393673110720561e-2 4.393673110720561e-2</k_point>
        <npw>1337</npw>
        <eigenvalues size="7">-2.565943153035536e-1 5.354372273634946e-2 1.341349293300979e-1 1.773198139767513e-1 2.523333265639980e-1 3.169694465376527e-1 3.262911722335054e-1</eigenvalues>
        <occupations size="7">1.000000000000000e0 1.000000000000000e0 9.999999857862097e-1 9.967650922321589e-1 1.516155784725864e-7 1.446860574690275e-15 1.008668336765068e-16</occupations>
      </ks_energies>
      <ks_energies>
        <k_point weight="1.388888888889e-2">-6.938893903907228e-18 -2.929115407147042e-2 2.929115407147042e-2</k_point>
        <npw>1331</npw>
        <eigenvalues size="7">-2.591913994643054e-1 1.061890589098754e-1 1.582149097732748e-1 1.880449775205291e-1 2.519026652598034e-1 3.026246151922082e-1 3.054620406096439e-1</eigenvalues>
        <occupations size="7">1.000000000000000e0 9.999999999951573e-1 9.999861755610468e-1 9.350013984359864e-1 1.714675944937388e-7 8.717515144577540e-14 3.875370458454635e-14</occupations>
      </ks_energies>
      <ks_energies>
        <k_point weight="6.944444444444e-3">5.858230814294084e-2 0.000000000000000e0 0.000000000000000e0</k_point>
        <npw>1327</npw>
        <eigenvalues size="7">-2.578460412045580e-1 8.034081342326688e-2 1.450221228567058e-1 1.450221439311140e-1 2.544899960990994e-1 3.004445040419546e-1 3.622360938936848e-1</eigenvalues>
        <occupations size="7">1.000000000000000e0 9.999999999999968e-1 9.999996811122822e-1 9.999996811103621e-1 8.187199592602010e-8 1.625211634482128e-13 3.495857968893784e-21</occupations>
      </ks_energies>
      <ks_energies>
        <k_point weight="2.777777777778e-2">7.322788517867604e-2 1.464557703573521e-2 -1.464557703573521e-2</k_point>
        <npw>1329</npw>
        <eigenvalues size="7">-2.529792682134808e-1 4.117752911528632e-2 1.267193211356932e-1 1.308602560409088e-1 2.552900814500840e-1 3.041214767022341e-1 3.846768200783147e-1</eigenvalues>
        <occupations size="7">1.000000000000000e0 1.000000000000000e0 9.999999982917533e-1 9.999999944233306e-1 6.514145945315216e-8 5.684024494924712e-14 5.741371140471720e-24</occupations>
      </ks_energies>
      <ks_energies>
        <k_point weight="2.777777777778e-2">8.787346221441126e-2 2.929115407147042e-2 -2.929115407147042e-2</k_point>
        <npw>1330</npw>
        <eigenvalues size="7">-2.406916084666241e-1 -7.341953526720029e-3 1.047609509871883e-1 1.211931935089372e-1 2.622576698196966e-1 3.142985511030897e-1 3.850500230335583e-1</eigenvalues>
        <occupations size="7">1.000000000000000e0 1.000000000000000e0 9.999999999967798e-1 9.999999996477541e-1 8.897957237654119e-9 3.103433470047680e-15 5.160681480659378e-24</occupations>
      </ks_energies>
      <ks_energies>
        <k_point weight="2.777777777778e-2">1.025190392501465e-1 4.393673110720564e-2 -4.393673110720564e-2</k_point>
        <npw>1328</npw>
        <eigenvalues size="7">-2.193413211539747e-1 -5.621037665541532e-2 8.526666102995978e-2 1.170480223905135e-1 2.597026694590966e-1 3.330759969747997e-1 3.927446156913610e-1</eigenvalues>
        <occupations size="7">1.000000000000000e0 1.000000000000000e0 9.999999999999877e-1 9.999999998922304e-1 1.846398023746006e-8 1.451641116320546e-17 5.727039259659138e-25</occupations>
      </ks_energies>
      <ks_energies>
        <k_point weight="2.777777777778e-2">-5.858230814294084e-2 -1.171646162858817e-1 1.171646162858817e-1</k_point>
        <npw>1336</npw>
        <eigenvalues size="7">-1.934873287911193e-1 -9.702253558498626e-2 7.080098130768132e-2 1.186979917447925e-1 2.569274734903372e-1 3.402573607485284e-1 3.843669177055509e-1</eigenvalues>
        <occupations size="7">1.000000000000000e0 1.000000000000000e0 9.999999999999998e-1 9.999999998273246e-1 4.080215634431954e-8 1.865374043889260e-18 6.272917713915682e-24</occupations>
      </ks_energies>
      <ks_energies>
        <k_point weight="2.777777777778e-2">-4.393673110720563e-2 -1.025190392501464e-1 1.025190392501464e-1</k_point>
        <npw>1331</npw>
        <eigenvalues size="7">-1.873466977105980e-1 -1.048208937542089e-1 6.244931142275271e-2 1.258754972032014e-1 2.577512809884778e-1 3.443315536532584e-1 3.749123959817716e-1</eigenvalues>
        <occupations size="7">1.000000000000000e0 1.000000000000000e0 1.000000000000000e0 9.999999986577130e-1 3.224494765955657e-8 5.824024805488125e-19 9.345999769481089e-23</occupations>
      </ks_energies>
      <ks_energies>
        <k_point weight="2.777777777778e-2">-2.929115407147042e-2 -8.787346221441126e-2 8.787346221441126e-2</k_point>
        <npw>1323</npw>
        <eigenvalues size="7">-2.107097315881009e-1 -7.003386273835512e-2 6.135545979807175e-2 1.377775285408524e-1 2.622640060817458e-1 3.504815839728103e-1 3.646095353953329e-1</eigenvalues>
        <occupations size="7">1.000000000000000e0 1.000000000000000e0 1.000000000000000e0 9.999999597562285e-1 8.881863299034363e-9 1.004851782160510e-19 1.774382875843993e-21</occupations>
      </ks_energies>
      <ks_energies>
        <k_point weight="2.777777777778e-2">-1.464557703573521e-2 -7.322788517867604e-2 7.322788517867604e-2</k_point>
        <npw>1332</npw>
        <eigenvalues size="7">-2.343849322697981e-1 -2.324541563747405e-2 6.970916285432033e-2 1.528327815555966e-1 2.685836774862906e-1 3.501495655417683e-1 3.538316890962749e-1</eigenvalues>
        <occupations size="7">1.000000000000000e0 1.000000000000000e0 9.999999999999998e-1 9.999970295962115e-1 1.459933624606359e-9 1.104842133404971e-19 3.858398692004105e-20</occupations>
      </ks_energies>
      <ks_energies>
        <k_point weight="1.388888888889e-2">6.938893903907228e-18 -5.858230814294084e-2 5.858230814294084e-2</k_point>
        <npw>1341</npw>
        <eigenvalues size="7">-2.495962595066902e-1 2.082838308704697e-2 9.267350632565808e-2 1.679606719996927e-1 2.699919184628840e-1 3.311152788332831e-1 3.375282546751639e-1</eigenvalues>
        <occupations size="7">1.000000000000000e0 1.000000000000000e0 9.999999999998980e-1 9.997762047744569e-1 9.763212548501327e-10 2.541869678323110e-17 4.068222553822114e-18</occupations>
      </ks_energies>
      <ks_energies>
        <k_point weight="6.944444444444e-3">8.787346221441126e-2 0.000000000000000e0 0.000000000000000e0</k_point>
        <npw>1331</npw>
        <eigenvalues size="7">-2.473204185357822e-1 2.305101444733272e-2 1.157591491351051e-1 1.157591695242857e-1 2.319070647959341e-1 3.022900065094640e-1 4.156557645949392e-1</eigenvalues>
        <occupations size="7">1.000000000000000e0 1.000000000000000e0 9.999999999254294e-1 9.999999999254289e-1 5.191542618660620e-5 9.592070020767483e-14 8.222805262668214e-28</occupations>
      </ks_energies>
      <ks_energies>
        <k_point weight="2.777777777778e-2">1.025190392501465e-1 1.464557703573521e-2 -1.464557703573521e-2</k_point>
        <npw>1321</npw>
        <eigenvalues size="7">-2.350092025982135e-1 -1.035970408551813e-2 9.516747824446572e-2 1.051087712919769e-1 2.365548691618086e-1 2.957964195082567e-1 4.194635980380633e-1</eigenvalues>
        <occupations size="7">1.000000000000000e0 1.000000000000000e0 9.999999999997923e-1 9.999999999964436e-1 1.375923215072479e-5 6.132866116519025e-13 2.770309401786109e-28</occupations>
      </ks_energies>
      <ks_energies>
        <k_point weight="2.777777777778e-2">1.171646162858817e-1 2.929115407147043e-2 -2.929115407147043e-2</k_point>
        <npw>1319</npw>
        <eigenvalues size="7">-2.146739787197411e-1 -4.854279313112246e-2 6.753239581992030e-2 1.001758831748873e-1 2.469916977571379e-1 3.136277537311021e-1 4.090900498175128e-1</eigenvalues>
        <occupations size="7">1.000000000000000e0 1.000000000000000e0 1.000000000000000e0 9.999999999991312e-1 6.975173176106733e-7 3.759046976457869e-15 5.366869826742368e-27</occupations>
      </ks_energies>
      <ks_energies>
        <k_point weight="2.777777777778e-2">-4.393673110720563e-2 -1.318101933216169e-1 1.318101933216169e-1</k_point>
        <npw>1318</npw>
        <eigenvalues size="7">-1.887793106962703e-1 -8.489791792417435e-2 4.356789382484153e-2 1.013978303436376e-1 2.500646885345651e-1 3.562969447965826e-1 4.032208670793854e-1</eigenvalues>
        <occupations size="7">1.000000000000000e0 1.000000000000000e0 1.000000000000000e0 9.999999999987681e-1 2.898983615522478e-7 1.907690750152107e-20 2.870737884320831e-26</occupations>
      </ks_energies>
      <ks_energies>
        <k_point weight="2.777777777778e-2">-2.929115407147042e-2 -1.171646162858817e-1 1.171646162858817e-1</k_point>
        <npw>1328</npw>
        <eigenvalues size="7">-1.730442595018801e-1 -1.027797938542702e-1 2.765889658582532e-2 1.085931900404463e-1 2.545560281733792e-1 3.844731810067652e-1 4.178521531361427e-1</eigenvalues>
        <occupations size="7">1.000000000000000e0 1.000000000000000e0 1.000000000000000e0 9.999999999903752e-1 8.034185330162659e-8 6.085328123510054e-24 4.390187076769632e-28</occupations>
      </ks_energies>
      <ks_energies>
        <k_point weight="2.777777777778e-2">-1.464557703573521e-2 -1.025190392501465e-1 1.025190392501465e-1</k_point>
        <npw>1326</npw>
        <eigenvalues size="7">-1.896271270872596e-1 -8.112348625777187e-2 2.289173662530200e-2 1.209585895693806e-1 2.626080380535051e-1 3.884681567243510e-1 4.012148242859594e-1</eigenvalues>
        <occupations size="7">1.000000000000000e0 1.000000000000000e0 1.000000000000000e0 9.999999996705913e-1 8.050357639594118e-9 1.943438865093094e-24 5.092272441600417e-26</occupations>
      </ks_energies>
      <ks_energies>
        <k_point weight="1.388888888889e-2">0.000000000000000e0 -8.787346221441126e-2 8.787346221441126e-2</k_point>
        <npw>1320</npw>
        <eigenvalues size="7">-2.146681014879324e-1 -4.827851761386908e-2 3.507381475444925e-2 1.368112985364180e-1 2.710973832049856e-1 3.773718712398180e-1 3.881036529211845e-1</eigenvalues>
        <occupations size="7">1.000000000000000e0 1.000000000000000e0 1.000000000000000e0 9.999999694645121e-1 7.119051013483656e-10 4.628538701380470e-23 2.156751077328715e-24</occupations>
      </ks_energies>
      <ks_energies>
        <k_point weight="6.944444444444e-3">1.171646162858817e-1 0.000000000000000e0 0.000000000000000e0</k_point>
        <npw>1331</npw>
        <eigenvalues size="7">-2.227907651404440e-1 -3.276982903745125e-2 9.312076553849648e-2 9.312087431681109e-2 2.183264183560999e-1 2.735780814121407e-1 4.707694357877071e-1</eigenvalues>
        <occupations size="7">1.000000000000000e0 1.000000000000000e0 9.999999999998844e-1 9.999999999998844e-1 2.508251526624718e-3 3.504344610378324e-10 1.192031248768104e-34</occupations>
      </ks_energies>
      <ks_energies>
        <k_point weight="2.777777777778e-2">1.318101933216169e-1 1.464557703573522e-2 -1.464557703573522e-2</k_point>
        <npw>1325</npw>
        <eigenvalues size="7">-2.033154725673162e-1 -6.194629771421907e-2 7.311631025944374e-2 8.681182321346675e-2 2.268250586970598e-1 2.688321418067166e-1 4.716887923084601e-1</eigenvalues>
        <occupations size="7">1.000000000000000e0 1.000000000000000e0 9.999999999999995e-1 9.999999999999808e-1 2.217272188752379e-4 1.359886399326872e-9 9.166637966382051e-35</occupations>
      </ks_energies>
      <ks_energies>
        <k_point weight="2.777777777778e-2">-2.929115407147042e-2 -1.464557703573521e-1 1.464557703573521e-1</k_point>
        <npw>1325</npw>
        <eigenvalues size="7">-1.781265594125458e-1 -9.068420719201413e-2 4.295457142851614e-2 8.682890661577087e-2 2.360156721617833e-1 2.986812801663656e-1 4.606255070877675e-1</eigenvalues>
        <occupations size="7">1.000000000000000e0 1.000000000000000e0 1.000000000000000e0 9.999999999999808e-1 1.605088554155228e-5 2.689664041219710e-13 2.162660190376073e-33</occupations>
      </ks_energies>
      <ks_energies>
        <k_point weight="2.777777777778e-2">-1.464557703573521e-2 -1.318101933216169e-1 1.318101933216169e-1</k_point>
        <npw>1325</npw>
        <eigenvalues size="7">-1.572426897438823e-1 -1.097974340332768e-1 1.761472401556888e-2 9.313765886430584e-2 2.419545709257051e-1 3.528143272328825e-1 4.511663801546910e-1</eigenvalues>
        <occupations size="7">1.000000000000000e0 1.000000000000000e0 1.000000000000000e0 9.999999999998835e-1 2.941586063138577e-6 5.159950925494304e-20 3.226382807039388e-32</occupations>
      </ks_energies>
      <ks_energies>
        <k_point weight="1.388888888889e-2">-6.938893903907228e-18 -1.171646162858817e-1 1.171646162858817e-1</k_point>
        <npw>1316</npw>
        <eigenvalues size="7">-1.667240306827896e-1 -9.845409127734028e-2 7.647352190642537e-3 1.050392900126469e-1 2.515646243108014e-1 4.137678599882418e-1 4.389042754922179e-1</eigenvalues>
        <occupations size="7">1.000000000000000e0 1.000000000000000e0 1.000000000000000e0 9.999999999965134e-1 1.888545998950306e-7 1.410194512331401e-27 1.072132788374547e-30</occupations>
      </ks_energies>
      <ks_energies>
        <k_point weight="6.944444444444e-3">1.464557703573521e-1 0.000000000000000e0 0.000000000000000e0</k_point>
        <npw>1330</npw>
        <eigenvalues size="7">-1.850595642140060e-1 -8.687997369441035e-2 7.890290880809479e-2 7.890292190123592e-2 2.159035807859240e-1 2.448949435729944e-1 5.225677576889281e-1</eigenvalues>
        <occupations size="7">1.000000000000000e0 1.000000000000000e0 9.999999999999980e-1 9.999999999999980e-1 4.999433685032440e-3 1.269780580517789e-6 4.455921525345834e-41</occupations>
      </ks_energies>
      <ks_energies>
        <k_point weight="2.777777777778e-2">-1.464557703573520e-2 -1.611013473930873e-1 1.611013473930873e-1</k_point>
        <npw>1325</npw>
        <eigenvalues size="7">-1.610641825078560e-1 -1.127337710313297e-1 6.185451197431611e-2 7.733659995835803e-2 2.261317608384998e-1 2.486855498515302e-1 5.219295210278862e-1</eigenvalues>
        <occupations size="7">1.000000000000000e0 1.000000000000000e0 1.000000000000000e0 9.999999999999986e-1 2.702870150892306e-4 4.299074134124976e-7 5.347275737040329e-41</occupations>
      </ks_energies>
      <ks_energies>
        <k_point weight="1.388888888889e-2">1.387778780781446e-17 -1.464557703573521e-1 1.464557703573521e-1</k_point>
        <npw>1326</npw>
        <eigenvalues size="7">-1.414836045719715e-1 -1.284866023470298e-1 3.445547622957817e-2 8.226057457538619e-2 2.322938654230831e-1 2.925656441016885e-1 5.010281965262359e-1</eigenvalues>
        <occupations size="7">1.000000000000000e0 1.000000000000000e0 1.000000000000000e0 9.999999999999948e-1 4.648394303515240e-5 1.543659337595773e-12 2.097275129258964e-38</occupations>
      </ks_energies>
      <ks_energies>
        <k_point weight="3.472222222222e-3">-1.757469244288225e-1 0.000000000000000e0 0.000000000000000e0</k_point>
        <npw>1338</npw>
        <eigenvalues size="7">-1.383994459138944e-1 -1.383994292256538e-1 7.405692071518809e-2 7.405692125669439e-2 2.249798280359436e-1 2.249798448083497e-1 5.504144670512463e-1</eigenvalues>
        <occupations size="7">1.000000000000000e0 1.000000000000000e0 9.999999999999995e-1 9.999999999999995e-1 3.755917312749375e-4 3.755899320761060e-4 1.561717997109153e-44</occupations>
      </ks_energies>
      <ks_energies>
        <k_point weight="2.777777777778e-2">5.858230814294084e-2 2.929115407147042e-2 0.000000000000000e0</k_point>
        <npw>1336</npw>
        <eigenvalues size="7">-2.563052089447499e-1 5.855244660827850e-2 1.259360328624073e-1 1.611760843144624e-1 2.804043935963337e-1 2.827752044536678e-1 3.535191143834688e-1</eigenvalues>
        <occupations size="7">1.000000000000000e0 1.000000000000000e0 9.999999986342949e-1 9.999677837996895e-1 4.983904896165124e-11 2.531568747370380e-11 4.218836214986154e-20</occupations>
      </ks_energies>
      <ks_energies>
        <k_point weight="5.555555555556e-2">7.322788517867604e-2 4.393673110720563e-2 -1.464557703573521e-2</k_point>
        <npw>1336</npw>
        <eigenvalues size="7">-2.475685350891305e-1 1.158006306200458e-2 1.010572265149281e-1 1.498739113043352e-1 2.751886061622974e-1 3.046517493210783e-1 3.713649350721265e-1</eigenvalues>
        <occupations size="7">1.000000000000000e0 1.000000000000000e0 9.999999999988823e-1 9.999987245384744e-1 2.211903788502459e-10 4.884920725182027e-14 2.575190691995932e-22</occupations>
      </ks_energies>
      <ks_energies>
        <k_point weight="5.555555555556e-2">8.787346221441126e-2 5.858230814294084e-2 -2.929115407147043e-2</k_point>
        <npw>1329</npw>
        <eigenvalues size="7">-2.297301323660340e-1 -3.950741155327563e-2 8.685199756306174e-2 1.369461613050357e-1 2.666675102256982e-1 3.229376115044436e-1 3.752141857508904e-1</eigenvalues>
        <occupations size="7">1.000000000000000e0 1.000000000000000e0 9.999999999999806e-1 9.999999682649495e-1 2.524056504195207e-9 2.629493364994591e-16 8.573900568908616e-23</occupations>
      </ks_energies>
      <ks_energies>
        <k_point weight="5.555555555556e-2">-7.322788517867604e-2 -1.025190392501465e-1 1.318101933216169e-1</k_point>
        <npw>1329</npw>
        <eigenvalues size="7">-2.042858738562862e-1 -8.605650373793496e-2 7.961878252350364e-2 1.275327275520668e-1 2.605974902452333e-1 3.276092244093390e-1 3.745906488078714e-1</eigenvalues>
        <occupations size="7">1.000000000000000e0 1.000000000000000e0 9.999999999999975e-1 9.999999978448306e-1 1.429855870618557e-8 6.921480829833198e-17 1.024588522564484e-22</occupations>
      </ks_energies>
      <ks_energies>
        <k_point weight="2.777777777778e-2">-5.858230814294084e-2 -8.787346221441126e-2 1.171646162858817e-1</k_point>
        <npw>1328</npw>
        <eigenvalues size="7">-1.871045443951111e-1 -1.103239312353115e-1 7.742896514645652e-2 1.241166977646660e-1 2.584633629536639e-1 3.277046843893414e-1 3.739060998448811e-1</eigenvalues>
        <occupations size="7">1.000000000000000e0 1.000000000000000e0 9.999999999999986e-1 9.999999991879061e-1 2.630895525276122e-8 6.735253574990132e-17 1.245922860313359e-22</occupations>
      </ks_energies>
      <ks_energies>
        <k_point weight="2.777777777778e-2">8.787346221441126e-2 2.929115407147042e-2 0.000000000000000e0</k_point>
        <npw>1330</npw>
        <eigenvalues size="7">-2.441303134991962e-1 9.967305790802794e-3 9.667672181658917e-2 1.247561328656860e-1 2.586148946396440e-1 3.055681664657327e-1 3.852872767607920e-1</eigenvalues>
        <occupations size="7">1.000000000000000e0 1.000000000000000e0 9.999999999996803e-1 9.999999990251226e-1 2.519422039541668e-8 3.759626386790041e-14 4.822448860845706e-24</occupations>
      </ks_energies>
      <ks_energies>
        <k_point weight="5.555555555556e-2">1.025190392501465e-1 4.393673110720563e-2 -1.464557703573522e-2</k_point>
        <npw>1326</npw>
        <eigenvalues size="7">-2.273324798658111e-1 -2.933720353026197e-2 7.207746220886707e-2 1.136156490913904e-1 2.710754705633935e-1 3.169153437171825e-1 3.764828760718273e-1</eigenvalues>
        <occupations size="7">1.000000000000000e0 1.000000000000000e0 9.999999999999998e-1 9.999999999595804e-1 7.163761460360856e-10 1.469399827739346e-15 5.966973350927428e-23</occupations>
      </ks_energies>
      <ks_energies>
        <k_point weight="5.555555555556e-2">-5.858230814294084e-2 -1.171646162858817e-1 1.464557703573521e-1</k_point>
        <npw>1318</npw>
        <eigenvalues size="7">-2.029628542184357e-1 -7.060178752288514e-2 5.487675807068869e-2 1.056466600564801e-1 2.730698177796716e-1 3.401071046526319e-1 3.828000083755308e-1</eigenvalues>
        <occupations size="7">1.000000000000000e0 1.000000000000000e0 1.000000000000000e0 9.999999999958526e-1 4.052045018834352e-10 1.947198953525671e-18 9.815178083059759e-24</occupations>
      </ks_energies>
      <ks_energies>
        <k_point weight="5.555555555556e-2">-4.393673110720561e-2 -1.025190392501465e-1 1.318101933216169e-1</k_point>
        <npw>1325</npw>
        <eigenvalues size="7">-1.800591271617550e-1 -1.012352073399022e-1 4.379322486517434e-2 1.049226261814115e-1 2.746998086422234e-1 3.417918716462419e-1 4.125363578077960e-1</eigenvalues>
        <occupations size="7">1.000000000000000e0 1.000000000000000e0 1.000000000000000e0 9.999999999966278e-1 2.543420991100707e-10 1.203254426103604e-18 2.004882414141512e-27</occupations>
      </ks_energies>
      <ks_energies>
        <k_point weight="5.555555555556e-2">-2.929115407147042e-2 -8.787346221441126e-2 1.171646162858817e-1</k_point>
        <npw>1330</npw>
        <eigenvalues size="7">-1.863717866543604e-1 -9.257336869829215e-2 3.932291247668345e-2 1.115939415864670e-1 2.795462474400543e-1 3.394565172453988e-1 4.089161369902888e-1</eigenvalues>
        <occupations size="7">1.000000000000000e0 1.000000000000000e0 1.000000000000000e0 9.999999999773156e-1 6.368718777606630e-11 2.344973314708089e-18 5.640282865599304e-27</occupations>
      </ks_energies>
      <ks_energies>
        <k_point weight="5.555555555556e-2">-1.464557703573521e-2 -7.322788517867604e-2 1.025190392501465e-1</k_point>
        <npw>1327</npw>
        <eigenvalues size="7">-2.117291158870450e-1 -5.583259544751938e-2 4.409160749240381e-2 1.239741762429400e-1 2.866999179017316e-1 3.349915941933191e-1 3.881175461875486e-1</eigenvalues>
        <occupations size="7">1.000000000000000e0 1.000000000000000e0 1.000000000000000e0 9.999999992203106e-1 8.248881062796093e-12 8.397771077925558e-18 2.148206813310804e-24</occupations>
      </ks_energies>
      <ks_energies>
        <k_point weight="2.777777777778e-2">1.040834085586084e-17 -5.858230814294084e-2 8.787346221441123e-2</k_point>
        <npw>1334</npw>
        <eigenvalues size="7">-2.336690370092578e-1 -1.780789118812619e-2 6.342611333719260e-2 1.388424655057211e-1 2.914716139005895e-1 3.149441820447474e-1 3.788247504527526e-1</eigenvalues>
        <occupations size="7">1.000000000000000e0 1.000000000000000e0 1.000000000000000e0 9.999999454442598e-1 2.110101073435720e-12 2.580654596276569e-15 3.056079411716000e-23</occupations>
      </ks_energies>
      <ks_energies>
        <k_point weight="2.777777777778e-2">1.171646162858817e-1 2.929115407147043e-2 -1.387778780781446e-17</k_point>
        <npw>1325</npw>
        <eigenvalues size="7">-2.187418593218366e-1 -3.896019807454320e-2 7.520295073964016e-2 9.406835035473316e-2 2.445428393332099e-1 2.884208539654139e-1 4.201852558398127e-1</eigenvalues>
        <occupations size="7">1.000000000000000e0 1.000000000000000e0 9.999999999999993e-1 9.999999999998483e-1 1.404168329575452e-6 5.044918727717082e-12 2.254145731181523e-28</occupations>
      </ks_energies>
      <ks_energies>
        <k_point weight="5.555555555556e-2">-4.393673110720563e-2 -1.318101933216169e-1 1.611013473930873e-1</k_point>
        <npw>1329</npw>
        <eigenvalues size="7">-1.954803847394751e-1 -7.018721247735336e-2 5.031449665749170e-2 8.546123103526245e-2 2.591876926655059e-1 3.076761502286192e-1 4.082484152093172e-1</eigenvalues>
        <occupations size="7">1.000000000000000e0 1.000000000000000e0 1.000000000000000e0 9.999999999999872e-1 2.139073841086123e-8 2.058625469215600e-14 6.825815829830617e-27</occupations>
      </ks_energies>
      <ks_energies>
        <k_point weight="5.555555555556e-2">-2.929115407147042e-2 -1.171646162858817e-1 1.464557703573521e-1</k_point>
        <npw>1322</npw>
        <eigenvalues size="7">-1.704080667789810e-1 -9.791319545674174e-2 2.778819505342955e-2 8.555703471094970e-2 2.647124154663302e-1 3.560576686604741e-1 3.978741942154207e-1</eigenvalues>
        <occupations size="7">1.000000000000000e0 1.000000000000000e0 1.000000000000000e0 9.999999999999867e-1 4.412607709213479e-9 2.042670641297600e-20 1.322607047228766e-25</occupations>
      </ks_energies>
      <ks_energies>
        <k_point weight="5.555555555556e-2">-1.464557703573521e-2 -1.025190392501465e-1 1.318101933216169e-1</k_point>
        <npw>1323</npw>
        <eigenvalues size="7">-1.661645638486357e-1 -1.007364781353430e-1 1.489194029308180e-2 9.351307116163632e-2 2.722401816171949e-1 3.841778360924535e-1 4.212169468475333e-1</eigenvalues>
        <occupations size="7">1.000000000000000e0 1.000000000000000e0 1.000000000000000e0 9.999999999998705e-1 5.135928269422044e-10 6.621122447341257e-24 1.678670663807722e-28</occupations>
      </ks_energies>
      <ks_energies>
        <k_point weight="2.777777777778e-2">0.000000000000000e0 -8.787346221441126e-2 1.171646162858817e-1</k_point>
        <npw>1325</npw>
        <eigenvalues size="7">-1.881513093864878e-1 -7.707278231637808e-2 1.838797440482456e-2 1.073783007385854e-1 2.823902218999954e-1 3.707585044685686e-1 3.942906552506368e-1</eigenvalues>
        <occupations size="7">1.000000000000000e0 1.000000000000000e0 1.000000000000000e0 9.999999999931982e-1 2.825920590237640e-11 3.062371063433742e-22 3.682062658601399e-25</occupations>
      </ks_energies>
      <ks_energies>
        <k_point weight="2.777777777778e-2">-2.929115407147041e-2 -1.464557703573521e-1 1.757469244288225e-1</k_point>
        <npw>1325</npw>
        <eigenvalues size="7">-1.813697259944988e-1 -8.810611807844143e-2 6.349323124408636e-2 7.287733255887868e-2 2.405085203919924e-1 2.639919071076663e-1 4.696495421945578e-1</eigenvalues>
        <occupations size="7">1.000000000000000e0 1.000000000000000e0 1.000000000000000e0 9.999999999999995e-1 4.446444124602143e-6 5.421244285204763e-9 1.641529422168578e-34</occupations>
      </ks_energies>
      <ks_energies>
        <k_point weight="5.555555555556e-2">-1.464557703573519e-2 -1.318101933216169e-1 1.611013473930873e-1</k_point>
        <npw>1323</npw>
        <eigenvalues size="7">-1.560161512560272e-1 -1.120548432597589e-1 3.833335545103878e-2 7.074320509403957e-2 2.532402362592652e-1 2.960036281979764e-1 4.573210939659553e-1</eigenvalues>
        <occupations size="7">1.000000000000000e0 1.000000000000000e0 1.000000000000000e0 9.999999999999998e-1 1.170067010536268e-7 5.780323867845252e-13 5.559215873430844e-33</occupations>
      </ks_energies>
      <ks_energies>
        <k_point weight="2.777777777778e-2">6.938893903907228e-18 -1.171646162858817e-1 1.464557703573521e-1</k_point>
        <npw>1326</npw>
        <eigenvalues size="7">-1.476313011840419e-1 -1.167890685275906e-1 1.651466127045186e-2 7.895888584592599e-2 2.610024858413053e-1 3.535709410622565e-1 4.438910264619810e-1</eigenvalues>
        <occupations size="7">1.000000000000000e0 1.000000000000000e0 1.000000000000000e0 9.999999999999980e-1 1.273616668247451e-8 4.156825529355954e-20 2.579121988201905e-31</occupations>
      </ks_energies>
      <ks_energies>
        <k_point weight="1.388888888889e-2">-1.757469244288225e-1 2.929115407147043e-2 0.000000000000000e0</k_point>
        <npw>1328</npw>
        <eigenvalues size="7">-1.364202142439186e-1 -1.364201905884763e-1 6.258529847425867e-2 6.258530776105444e-2 2.471429103822052e-1 2.471443807956078e-1 5.168217691226787e-1</eigenvalues>
        <occupations size="7">1.000000000000000e0 1.000000000000000e0 1.000000000000000e0 1.000000000000000e0 6.680237747419899e-7 6.677431849849061e-7 2.301036830888793e-40</occupations>
      </ks_energies>
      <ks_energies>
        <k_point weight="2.777777777778e-2">-5.858230814294084e-2 -1.171646162858817e-1 1.757469244288225e-1</k_point>
        <npw>1329</npw>
        <eigenvalues size="7">-2.067604747434041e-1 -5.549088434631121e-2 4.374460598267683e-2 9.923338734448530e-2 3.014624553237288e-1 3.173664068257011e-1 3.639146416017980e-1</eigenvalues>
        <occupations size="7">1.000000000000000e0 1.000000000000000e0 1.000000000000000e0 9.999999999993364e-1 1.215061655219992e-13 1.291725424592411e-15 2.164076628112424e-21</occupations>
      </ks_energies>
      <ks_energies>
        <k_point weight="5.555555555556e-2">-4.393673110720563e-2 -1.025190392501464e-1 1.611013473930873e-1</k_point>
        <npw>1328</npw>
        <eigenvalues size="7">-1.814915594100466e-1 -8.515589450611980e-2 2.829424534069801e-2 8.612724918864169e-2 3.097554355358612e-1 3.353140262524045e-1 3.748625926554724e-1</eigenvalues>
        <occupations size="7">1.000000000000000e0 1.000000000000000e0 1.000000000000000e0 9.999999999999842e-1 1.136504127177242e-14 7.658704754242284e-18 9.479939566577517e-23</occupations>
      </ks_energies>
      <ks_energies>
        <k_point weight="2.777777777778e-2">-2.929115407147042e-2 -8.787346221441126e-2 1.464557703573521e-1</k_point>
        <npw>1324</npw>
        <eigenvalues size="7">-1.655827994744996e-1 -1.029325617632377e-1 2.383497119913522e-2 8.102901877988677e-2 3.102730133608447e-1 3.351640238655466e-1 4.273695138219852e-1</eigenvalues>
        <occupations size="7">1.000000000000000e0 1.000000000000000e0 1.000000000000000e0 9.999999999999964e-1 9.802747565528811e-15 7.994075478479267e-18 2.894206624568088e-29</occupations>
      </ks_energies>
      <ks_energies>
        <k_point weight="2.777777777778e-2">-2.929115407147040e-2 -1.171646162858817e-1 1.757469244288225e-1</k_point>
        <npw>1326</npw>
        <eigenvalues size="7">-1.713168460552382e-1 -9.321491318779776e-2 3.648742363947771e-2 6.525975363863175e-2 2.960810783903906e-1 3.109205805667786e-1 3.946364771731548e-1</eigenvalues>
        <occupations size="7">1.000000000000000e0 1.000000000000000e0 1.000000000000000e0 1.000000000000000e0 5.653818102088907e-13 8.146949058495965e-15 3.335647577349729e-25</occupations>
      </ks_energies>
      <ks_energies>
        <k_point weight="5.555555555556e-2">-1.464557703573520e-2 -1.025190392501465e-1 1.611013473930873e-1</k_point>
        <npw>1324</npw>
        <eigenvalues size="7">-1.499556556495213e-1 -1.122508552475747e-1 2.370625329123514e-2 5.857269730153371e-2 3.083712541954995e-1 3.579877907534971e-1 3.836455501863849e-1</eigenvalues>
        <occupations size="7">1.000000000000000e0 1.000000000000000e0 1.000000000000000e0 1.000000000000000e0 1.687819364245237e-14 1.176794991689575e-20 7.708677150189227e-24</occupations>
      </ks_energies>
      <ks_energies>
        <k_point weight="2.777777777778e-2">1.387778780781446e-17 -8.787346221441126e-2 1.464557703573521e-1</k_point>
        <npw>1326</npw>
        <eigenvalues size="7">-1.583255878505668e-1 -1.036161028282401e-1 1.767459146295944e-2 6.791319727452340e-2 3.173780589863938e-1 3.651863126686496e-1 3.801451060231218e-1</eigenvalues>
        <occupations size="7">1.000000000000000e0 1.000000000000000e0 1.000000000000000e0 1.000000000000000e0 1.287432177296493e-15 1.504798767910549e-21 2.095701637486622e-23</occupations>
      </ks_energies>
      <ks_energies>
        <k_point weight="1.388888888889e-2">-1.757469244288225e-1 5.858230814294084e-2 0.000000000000000e0</k_point>
        <npw>1324</npw>
        <eigenvalues size="7">-1.321631576750917e-1 -1.321631172850272e-1 4.352987244096775e-2 4.352991496553773e-2 2.996034217277935e-1 2.996034540449580e-1 4.445680565356814e-1</eigenvalues>
        <occupations size="7">1.000000000000000e0 1.000000000000000e0 1.000000000000000e0 1.000000000000000e0 2.066687897932803e-13 2.066668815308716e-13 2.125510188888836e-31</occupations>
      </ks_energies>
      <ks_energies>
        <k_point weight="6.944444444444e-3">-1.757469244288225e-1 8.787346221441123e-2 0.000000000000000e0</k_point>
        <npw>1316</npw>
        <eigenvalues size="7">-1.298582107348867e-1 -1.298582102171286e-1 3.510906606908197e-2 3.510914728722519e-2 3.592219645717742e-1 3.592229696089464e-1 3.772003659900644e-1</eigenvalues>
        <occupations size="7">1.000000000000000e0 1.000000000000000e0 1.000000000000000e0 1.000000000000000e0 8.271026597691243e-21 8.268651884608802e-21 4.860992829519095e-23</occupations>
      </ks_energies>
    </band_structure>
    <forces rank="2" dims="3 2" order="F">
      -1.732998473684122e-32 -5.776661578947072e-33 2.888330789473536e-32
      1.732998473684122e-32 5.776661578947072e-33 -2.888330789473536e-32
      </forces>
    <stress rank="2" dims="3 3" order="F">
      -6.908952053143080e-5 3.388131789017201e-20 2.032879073410321e-20
      2.710505431213761e-20 -6.908952053143081e-5 5.421010862427522e-20
      2.710505431213761e-20 5.421010862427522e-20 -6.908952053143081e-5
      </stress>
  </output>
  <status>0</status>
  <cputime>12</cputime>
  <closed DATE="15 Sep 2020" TIME="21:33:50"></closed>
</qes:espresso>
